LICENSE
README.md
pyproject.toml
setup.cfg
setup.py
orm/__init__.py
orm.base.egg-info/PKG-INFO
orm.base.egg-info/SOURCES.txt
orm.base.egg-info/dependency_links.txt
orm.base.egg-info/namespace_packages.txt
orm.base.egg-info/requires.txt
orm.base.egg-info/top_level.txt
orm/base/__init__.py