Metadata-Version: 2.1
Name: orm.base
Version: 1.0.1
Summary: A simple framework for wrapping any ORM.
Author: Siva Cn
Author-email: Siva Cn <cnsiva@protonmail.com>
Maintainer-email: Siva Cn <cnsiva@protonmail.com>
License: MIT-3-Clause
Project-URL: Documentation, https://github.com/SivaCn/orm.base
Project-URL: Source Code, https://github.com/SivaCn/orm.base
Project-URL: Bug Tracker, https://github.com/SivaCn/orm.base/issues
Platform: any
Classifier: Development Status :: 3 - Alpha
Classifier: Environment :: Web Environment
Classifier: Operating System :: OS Independent
Classifier: Programming Language :: Python
Classifier: Intended Audience :: Developers
Classifier: License :: OSI Approved :: MIT License
Classifier: Topic :: Software Development :: Libraries :: Application Frameworks
Requires-Python: >=2.7
License-File: LICENSE
